resolve_hash-0.1.0.data/scripts/resolve-hash
resolvehash/__init__.py
resolvehash/resolvehash.py
resolvehash/search/__init__.py
resolvehash/search/vcs.py
resolvehash/vcs/__init__.py
resolvehash/vcs/gerrit.py
resolvehash/vcs/github.py
resolvehash/vcs/gitlab.py
resolvehash/vcs/phabricator.py
resolve_hash-0.1.0.dist-info/LICENSE
resolve_hash-0.1.0.dist-info/METADATA
resolve_hash-0.1.0.dist-info/WHEEL
resolve_hash-0.1.0.dist-info/top_level.txt
resolve_hash-0.1.0.dist-info/RECORD
