Metadata-Version: 2.1
Name: resolve-hash
Version: 0.1.0
Summary: Resolve hash
Home-page: https://devcentral.nasqueron.org/source/resolve-hash/
Author: Sébastien Santoro
Author-email: dereckson@espace-win.org
License: UNKNOWN
Project-URL: Bug Tracker, https://devcentral.nasqueron.org/tag/resolve_hash/
Platform: UNKNOWN
Classifier: Programming Language :: Python :: 3
Classifier: License :: OSI Approved :: BSD License
Classifier: Operating System :: OS Independent
Classifier: Environment :: Console
Classifier: Intended Audience :: Developers
Classifier: Topic :: Software Development :: Version Control
Requires-Python: >=3.6
License-File: LICENSE
Requires-Dist: PyYAML (<7.0,>=6.0)
Requires-Dist: requests (<3.0,>=2.27.1)
